grant_funding_assistant/__init__.py
grant_funding_assistant/main.py
grant_funding_assistant-0.4.dist-info/METADATA
grant_funding_assistant-0.4.dist-info/WHEEL
grant_funding_assistant-0.4.dist-info/entry_points.txt
grant_funding_assistant-0.4.dist-info/top_level.txt
grant_funding_assistant-0.4.dist-info/RECORD
