Metadata-Version: 2.1
Name: grant-funding-assistant
Version: 0.4
Summary: This is a multiagent system which can help researchers create grant funding proposals based on their research profile and funding guidelines
Home-page: https://github.com/Dorcatz123/grant_funding_assistant
Author: Akshay P R
Author-email: akshaypr314159@gmail.com
Classifier: Programming Language :: Python :: 3
Classifier: License :: OSI Approved :: MIT License
Classifier: Operating System :: OS Independent
Requires-Python: >=3.10
Requires-Dist: crewai
Requires-Dist: crewai-tools
Requires-Dist: langchain-community
Requires-Dist: Ipython
